dq_summary_llm/__init__.py
dq_summary_llm/main.py
dq_summary_llm-0.1.dist-info/METADATA
dq_summary_llm-0.1.dist-info/WHEEL
dq_summary_llm-0.1.dist-info/top_level.txt
dq_summary_llm-0.1.dist-info/RECORD
