Metadata-Version: 2.1
Name: dq-summary-llm
Version: 0.1
Author: Sivananda Panda
Author-email: pandasivananda@gmail.com
Requires-Dist: pandas
Requires-Dist: openai
